README.md
setup.py
./cogment_agent_toolbox/__init__.py
./cogment_agent_toolbox/meta_data_pb2.py
./cogment_agent_toolbox/meta_data_pb2_grpc.py
./cogment_agent_toolbox/tensor_generator.py
./cogment_agent_toolbox/version.py
./cogment_agent_toolbox/api/__init__.py
cogment_agent_toolbox.egg-info/PKG-INFO
cogment_agent_toolbox.egg-info/SOURCES.txt
cogment_agent_toolbox.egg-info/dependency_links.txt
cogment_agent_toolbox.egg-info/requires.txt
cogment_agent_toolbox.egg-info/top_level.txt