Metadata-Version: 2.1
Name: cogment-agent-toolbox
Version: 0.0.4
Summary: Cogment Agent Toollbox
Home-page: https://gitlab.com/ai-r/agent-toolbox
Author: Artificial Intelligence Redefined
Author-email: dev+cogment@ai-r.com
License: Apache License 2.0
Platform: UNKNOWN
